npm/__init__.py
npm/finders.py
npm/management/__init__.py
npm/management/commands/__init__.py
npm/management/commands/npm_install.py
django_npm-1.0.1.dist-info/LICENSE
django_npm-1.0.1.dist-info/METADATA
django_npm-1.0.1.dist-info/WHEEL
django_npm-1.0.1.dist-info/top_level.txt
django_npm-1.0.1.dist-info/RECORD
