Metadata-Version: 2.1
Name: django-npm
Version: 1.0.1
Summary: A django staticfiles finder that uses npm
Home-page: https://github.com/kevin1024/django-npm
Author: Kevin McCarthy
Author-email: me@kevinmccarthy.org
License: MIT
Keywords: django npm staticfiles
Classifier: Development Status :: 3 - Alpha
Classifier: Intended Audience :: Developers
Classifier: Topic :: Software Development :: Build Tools
Classifier: License :: OSI Approved :: MIT License
Classifier: Programming Language :: Python :: 2
Classifier: Programming Language :: Python :: 2.6
Classifier: Programming Language :: Python :: 2.7
Classifier: Programming Language :: Python :: 3
Classifier: Programming Language :: Python :: 3.2
Classifier: Programming Language :: Python :: 3.3
Classifier: Programming Language :: Python :: 3.4
Classifier: Programming Language :: Python :: 3.12
License-File: LICENSE
Provides-Extra: test
Requires-Dist: pytest; extra == "test"
